pyfigure/__init__.py
pyfigure/types.py
pyfigure-2.7.1.dist-info/LICENSE
pyfigure-2.7.1.dist-info/METADATA
pyfigure-2.7.1.dist-info/WHEEL
pyfigure-2.7.1.dist-info/top_level.txt
pyfigure-2.7.1.dist-info/RECORD
