Metadata-Version: 2.1
Name: pyfigure
Version: 2.7.1
Summary: Generate configuration files for classes.
Author: Stefan Nešić
Project-URL: repository, https://gitlab.com/Soumeh/pyfigure
Keywords: classes,configuration
Classifier: Programming Language :: Python :: 3
Classifier: License :: OSI Approved :: MIT License
Classifier: Operating System :: OS Independent
Requires-Python: >=3.6
License-File: LICENSE
Requires-Dist: tomlkit
Requires-Dist: typeguard
Requires-Dist: superdict
